codec_fix.py
duotone.py
halftone.py
main.py
siss-0.1.4.dist-info/licenses/LICENSE
utils/__init__.py
utils/video_processing.py
siss-0.1.4.dist-info/METADATA
siss-0.1.4.dist-info/WHEEL
siss-0.1.4.dist-info/entry_points.txt
siss-0.1.4.dist-info/top_level.txt
siss-0.1.4.dist-info/RECORD
