Metadata-Version: 2.4
Name: siss
Version: 0.1.4
Summary: A command-line utility for applying artistic effects to videos
Home-page: https://github.com/MichailSemoglou/siss
Author: Michail Semoglou
Author-email: m.semoglou@qide.studio
License: MIT
Project-URL: Bug Reports, https://github.com/MichailSemoglou/siss/issues
Project-URL: Source, https://github.com/MichailSemoglou/siss
Keywords: video,duotone,halftone,effect,artistic,video-processing
Classifier: Development Status :: 3 - Alpha
Classifier: Intended Audience :: Developers
Classifier: Intended Audience :: End Users/Desktop
Classifier: Topic :: Multimedia :: Video
Classifier: Topic :: Artistic Software
Classifier: Operating System :: OS Independent
Classifier: Programming Language :: Python :: 3
Classifier: Programming Language :: Python :: 3.6
Classifier: Programming Language :: Python :: 3.7
Classifier: Programming Language :: Python :: 3.8
Classifier: Programming Language :: Python :: 3.9
Classifier: License :: OSI Approved :: MIT License
Requires-Python: >=3.6
License-File: LICENSE
Requires-Dist: opencv-python>=4.5.0
Requires-Dist: numpy>=1.20.0
Requires-Dist: tqdm>=4.60.0
Dynamic: author
Dynamic: author-email
Dynamic: classifier
Dynamic: description
Dynamic: description-content-type
Dynamic: home-page
Dynamic: keywords
Dynamic: license
Dynamic: license-file
Dynamic: project-url
Dynamic: requires-dist
Dynamic: requires-python
Dynamic: summary
